roselabs_canary/__init__.py
roselabs_canary/py.typed
roselabs_canary-1.0.1.dist-info/METADATA
roselabs_canary-1.0.1.dist-info/WHEEL
roselabs_canary-1.0.1.dist-info/RECORD
