Metadata-Version: 2.4
Name: roselabs-canary
Version: 1.0.1
Summary: Canary SDK for Python - Dependency vulnerability scanning
Project-URL: Homepage, https://canary.roselabs.io
Project-URL: Repository, https://github.com/roselabs/canary
Project-URL: Documentation, https://canary.roselabs.io/docs
Author-email: Rose Labs <support@roselabs.io>
License-Expression: MIT
Keywords: canary,dependencies,roselabs,scan,security,vulnerabilities
Classifier: Development Status :: 4 - Beta
Classifier: Intended Audience :: Developers
Classifier: License :: OSI Approved :: MIT License
Classifier: Operating System :: OS Independent
Classifier: Programming Language :: Python :: 3
Classifier: Programming Language :: Python :: 3.9
Classifier: Programming Language :: Python :: 3.10
Classifier: Programming Language :: Python :: 3.11
Classifier: Programming Language :: Python :: 3.12
Classifier: Topic :: Security
Classifier: Topic :: Software Development :: Libraries :: Python Modules
Requires-Python: >=3.9
Requires-Dist: httpx>=0.25.0
Provides-Extra: dev
Requires-Dist: pytest-asyncio>=0.21.0; extra == 'dev'
Requires-Dist: pytest>=7.0.0; extra == 'dev'
Requires-Dist: ruff>=0.1.0; extra == 'dev'
